cmem_plugin_ulid/__init__.py
cmem_plugin_ulid/ulid.py
cmem_plugin_ulid-2.0.0.dist-info/METADATA
cmem_plugin_ulid-2.0.0.dist-info/WHEEL
cmem_plugin_ulid-2.0.0.dist-info/licenses/LICENSE
cmem_plugin_ulid-2.0.0.dist-info/RECORD
